{"pose_4_low":{"mouth_dx":118.0,"mouth_dy_expr_offsets":{"1":0.0},"mouth_dy_offsets":{"pose_1431.png":0.0},"mouth_dy":58.0,"eyes_files":{},"body_file":"pose_1452.png","eyes_dx_offsets":{"pose_1411.png":0.0},"eyes_dx":116.0,"eyes_dy_offsets":{"pose_1411.png":0.0},"eyes_dy":46.0,"body_dx_offsets":{"pose_1452.png":0.0},"body_dx":0.0,"body_dy_offsets":{"pose_1452.png":0.0},"body_dy":0.0,"face_over_mouth":false,"face_file":"pose_1405.png","face_dx_offsets":{"pose_1405.png":0.0},"face_dx":86.0,"face_dy_offsets":{"pose_1405.png":0.0},"face_dy":15.0,"mouth_files":{"1":"pose_1436.png"},"mouth_dx_expr_offsets":{"1":0.0},"mouth_dx_offsets":{"pose_1431.png":0.0}},"pose_3_low":{"mouth_dx":45.0,"mouth_dy_expr_offsets":{"1":0.0},"mouth_dy_offsets":{"pose_1336.png":2.0},"mouth_dy":-47.0,"eyes_files":{"1":"pose_1311.png"},"body_file":"pose_1310.png","eyes_dx_expr_offsets":{"1":0.0},"eyes_dx_offsets":{"pose_1311.png":19.0,"pose_1411.png":-1.0},"eyes_dx":43.0,"eyes_dy_expr_offsets":{"1":0.0},"eyes_dy_offsets":{"pose_1311.png":-1.0,"pose_1411.png":0.0},"eyes_dy":-61.0,"body_dx_offsets":{"pose_1310.png":0.0,"pose_1452.png":0.0},"body_dx":0.0,"body_dy_offsets":{"pose_1310.png":0.0,"pose_1452.png":0.0},"body_dy":0.0,"face_over_mouth":false,"face_file":"pose_1305.png","face_dx_offsets":{"pose_1305.png":0.0,"pose_1405.png":0.0},"face_dx":8.0,"face_dy_offsets":{"pose_1305.png":0.0,"pose_1405.png":0.0},"face_dy":-94.0,"mouth_files":{"1":"pose_1336.png"},"mouth_dx_expr_offsets":{"1":0.0},"mouth_dx_offsets":{"pose_1336.png":0.0}},"pose_1_low":{"mouth_dx":42.0,"mouth_dy_expr_offsets":{"1":0.0},"mouth_dy":-50.0,"face_over_mouth":false,"eyes_files":{},"face_file":"pose_1105.png","body_file":"pose_1110.png","face_dx":10.0,"eyes_dx":40.0,"face_dy":-93.0,"eyes_dy":-62.0,"mouth_files":{"1":"pose_1136.png"},"body_dx":0.0,"body_dy":0.0,"mouth_dx_expr_offsets":{"1":0.0}},"pose_4_high":{"mouth_dx":4.0,"mouth_dy_expr_offsets":{"1":0.0},"mouth_dy_offsets":{"pose_1481.png":0.0},"mouth_dy":43.0,"eyes_files":{},"body_file":"pose_1500.png","eyes_dx_offsets":{"pose_1461.png":0.0},"eyes_dx":61.0,"eyes_dy_offsets":{"pose_1461.png":0.0},"eyes_dy":31.0,"body_dx_offsets":{"pose_1500.png":0.0},"body_dx":0.0,"body_dy_offsets":{"pose_1500.png":0.0},"body_dy":0.0,"face_over_mouth":false,"face_file":"pose_1455.png","face_dx_offsets":{"pose_1455.png":0.0},"face_dx":16.0,"face_dy_offsets":{"pose_1455.png":0.0},"face_dy":0.0,"mouth_files":{"1":"pose_1486.png"},"mouth_dx_expr_offsets":{"1":0.0},"mouth_dx_offsets":{"pose_1481.png":0.0}},"pose_1_high":{"mouth_dx":-16.0,"mouth_dy_expr_offsets":{"1":0.0},"mouth_dy":-50.0,"face_over_mouth":false,"eyes_files":{},"face_file":"pose_1155.png","body_file":"pose_1160.png","face_dx":34.0,"eyes_dx":41.0,"face_dy":-93.0,"eyes_dy":-62.0,"mouth_files":{"1":"pose_1186.png"},"body_dx":0.0,"body_dy":0.0,"mouth_dx_expr_offsets":{"1":0.0}},"pose_3_high":{"mouth_dx":73.0,"mouth_dy_expr_offsets":{"1":0.0},"mouth_dy_offsets":{"pose_1381.png":0.0},"mouth_dy":60.0,"eyes_files":{},"body_file":"pose_1401.png","eyes_dx_offsets":{"pose_1361.png":0.0},"eyes_dx":132.0,"eyes_dy_offsets":{"pose_1361.png":0.0},"eyes_dy":47.0,"body_dx_offsets":{"pose_1401.png":0.0},"body_dx":0.0,"body_dy_offsets":{"pose_1401.png":0.0},"body_dy":0.0,"face_over_mouth":false,"face_file":"pose_1355.png","face_dx_offsets":{"pose_1355.png":0.0},"face_dx":17.0,"face_dy_offsets":{"pose_1355.png":0.0},"face_dy":14.0,"mouth_files":{"1":"pose_1386.png"},"mouth_dx_expr_offsets":{"1":0.0},"mouth_dx_offsets":{"pose_1381.png":0.0}},"pose_2_high":{"mouth_dx":-47.0,"mouth_dy_expr_offsets":{"1":0.0},"mouth_dy":-68.0,"face_over_mouth":false,"eyes_files":{},"face_file":"pose_1255.png","body_file":"pose_1260.png","face_dx":4.0,"eyes_dx":11.0,"face_dy":-118.0,"eyes_dy":-83.0,"mouth_files":{"1":"pose_1286.png"},"body_dx":0.0,"body_dy":0.0,"mouth_dx_expr_offsets":{"1":0.0}},"pose_2_low":{"mouth_dx":66.0,"mouth_dy_expr_offsets":{"1":0.0},"mouth_dy":-68.0,"face_over_mouth":false,"eyes_files":{},"face_file":"pose_1205.png","body_file":"pose_1210.png","face_dx":7.0,"eyes_dx":66.0,"face_dy":-118.0,"eyes_dy":-80.0,"mouth_files":{"1":"pose_1236.png"},"body_dx":0.0,"body_dy":0.0,"mouth_dx_expr_offsets":{"1":0.0}}}